supSMSGecko/__init__.py
supSMSGecko/consts.py
supSMSGecko/lib.py
supSMSGecko/symbols.py
supSMSGecko/ldscript/GMSE01.ld
supSMSGecko/ldscript/GMSJ01.ld
supSMSGecko/ldscript/GMSJ0A.ld
supSMSGecko/ldscript/GMSP01.ld
supSMSGecko-0.1.0a5.dist-info/LICENSE
supSMSGecko-0.1.0a5.dist-info/METADATA
supSMSGecko-0.1.0a5.dist-info/WHEEL
supSMSGecko-0.1.0a5.dist-info/top_level.txt
supSMSGecko-0.1.0a5.dist-info/RECORD
